imageGenie/__init__.py
imageGenie/classify.py
imageGenie/constants.py
imageGenie/customNet.py
imageGenie/trainingModule.py
imageGenie-0.0.7.dist-info/LICENCE
imageGenie-0.0.7.dist-info/METADATA
imageGenie-0.0.7.dist-info/WHEEL
imageGenie-0.0.7.dist-info/top_level.txt
imageGenie-0.0.7.dist-info/RECORD
