Metadata-Version: 2.1
Name: imageGenie
Version: 0.0.7
Summary: State of the Art low-code Deep Learning Package for Image Classification
Home-page: https://github.com/ravi0531rp/imageGenie
Author: Ravi Prakash
Author-email: ravi.0531.rp@gmail.com
License: UNKNOWN
Platform: UNKNOWN
Classifier: Programming Language :: Python :: 3
Classifier: License :: OSI Approved :: MIT License
Classifier: Operating System :: OS Independent
Requires-Python: >3.7
License-File: LICENCE
Requires-Dist: opencv-contrib-python (==4.5.5.62)
Requires-Dist: tensorflow-gpu (==2.8.0)
Requires-Dist: Pillow
Requires-Dist: scipy
